{
  "name": "Telecomunicazioni",
  "layers": [
    {
      "name": "Router FreeWiFiGenova",
      "layer": "SITGEO:WI-FI_URBANO",
      "layer_url_wfs": "./GeoJson/free-wifi-router.geojson",
      "style": {
        "color": "#f7cb90",
        "opacity": 0.5
      },
      "tags": [
        "città",
        "servizi",
        "ospedali"
      ],
      "relevant_properties": [
        {
          "property_name": "NOME",
          "display_name": "Nome",
          "type": "string"
        },
        {
          "property_name": "SITO",
          "display_name": "Sito",
          "type": "string"
        },
        {
          "property_name": "TIPO",
          "display_name": "Tipo",
          "type": "string"
        },
        {
          "property_name": "MUNICIPIO",
          "display_name": "Municipio",
          "type": "number"
        },
        {
          "property_name": "ANNO",
          "display_name": "Anno installazione",
          "type": "string"
        }
      ],
      "components": [
        "app-opacity-slider"
      ]
    },
    {
      "name": "Impianti telecomunicazione",
      "layer": "L7991",
      "layer_url_wfs": "https://geoservizi.regione.liguria.it/geoserver/M2196/wms",
      "style": {
        "color": "#e597ca",
        "opacity": 0.5
      },
      "tags": [
        "città",
        "servizi",
        "ospedali"
      ],
      "relevant_properties": [
        {
          "property_name": "d_comune",
          "display_name": "Comune",
          "type": "string"
        },
        {
          "property_name": "d_provincia",
          "display_name": "Provincia",
          "type": "string"
        },
        {
          "property_name": "d_gestore",
          "display_name": "Gestore",
          "type": "string"
        },
        {
          "property_name": "d_sito",
          "display_name": "Indirizzo",
          "type": "string"
        },
        {
          "property_name": "localita",
          "display_name": "Località",
          "type": "string"
        },
        {
          "property_name": "descrizione",
          "display_name": "Descrizione",
          "type": "string"
        },
        {
          "property_name": "MUNICIPIO",
          "display_name": "Municipio",
          "type": "number"
        },
        {
          "property_name": "ANNO",
          "display_name": "Anno installazione",
          "type": "string"
        }
      ],
      "components": [
        "app-opacity-slider"
      ]
    }
  ]
}